sktaip_api/README.md
sktaip_api/__init__.py
sktaip_api/enum.py
sktaip_api/graphapp_manager.py
sktaip_api/playground_login.py
sktaip_api/schema.py
sktaip_api/server.py
sktaip_api/subapp_manager.py
sktaip_api/utils.py
sktaip_api-0.1.9.dist-info/METADATA
sktaip_api-0.1.9.dist-info/WHEEL
sktaip_api-0.1.9.dist-info/RECORD
