Metadata-Version: 2.1
Name: sktaip-api
Version: 0.1.9
Summary: AIX Platform Agent API Server for Deployment
License: Proprietary
Author: AIX Enterprise
Requires-Python: >=3.10,<4.0
Classifier: License :: Other/Proprietary License
Classifier: Programming Language :: Python :: 3
Classifier: Programming Language :: Python :: 3.10
Classifier: Programming Language :: Python :: 3.11
Classifier: Programming Language :: Python :: 3.12
Classifier: Programming Language :: Python :: 3.13
Requires-Dist: alembic (>=1.13.2,<2.0.0)
Requires-Dist: asyncpg (>=0.29.0,<0.30.0)
Requires-Dist: authlib (>=1.3.2,<2.0.0)
Requires-Dist: autologging (>=1.3.2,<2.0.0)
Requires-Dist: azure-identity (>=1.18.0,<2.0.0)
Requires-Dist: azure-search-documents (>=11.5.1,<12.0.0)
Requires-Dist: coverage (>=7.6.1,<8.0.0)
Requires-Dist: dependency-injector (>=4.41.0,<5.0.0)
Requires-Dist: fastapi (>=0.112.2,<0.113.0)
Requires-Dist: fastapi-authz (>=1.0.0,<2.0.0)
Requires-Dist: fastapi-keycloak (>=1.0.11,<2.0.0)
Requires-Dist: fastapi-versioning (==0.10.0)
Requires-Dist: greenlet (>=3.0.3,<4.0.0)
Requires-Dist: gunicorn (>=23.0.0,<24.0.0)
Requires-Dist: httpx (>=0.27.2,<0.28.0)
Requires-Dist: isort (>=5.13.2,<6.0.0)
Requires-Dist: kubernetes (>=30.1.0,<31.0.0)
Requires-Dist: langchain (>=0.3.0,<0.4.0)
Requires-Dist: langchain-community (>=0.3.0,<0.4.0)
Requires-Dist: langchain-openai (>=0.2.0,<0.3.0)
Requires-Dist: langgraph (>=0.2.26,<0.3.0)
Requires-Dist: langserve[all] (>=0.3.0,<0.4.0)
Requires-Dist: opensearch-py (==2.6.0)
Requires-Dist: passlib (>=1.7.4,<2.0.0)
Requires-Dist: pre-commit (>=3.8.0,<4.0.0)
Requires-Dist: psycopg[binary,pool] (>=3.2.1,<4.0.0)
Requires-Dist: ptvsd (>=4.3.2,<5.0.0)
Requires-Dist: pydantic-settings (>=2.4.0,<3.0.0)
Requires-Dist: pydantic[email] (>=2.10.0,<2.11.0)
Requires-Dist: pydevd (>=3.1.0,<4.0.0)
Requires-Dist: pyinstrument (>=5.0.1,<6.0.0)
Requires-Dist: pyjwt (>=2.8.0,<3.0.0)
Requires-Dist: pytest (>=8.3.2,<9.0.0)
Requires-Dist: pytest-asyncio (>=0.23.8,<0.24.0)
Requires-Dist: python-dotenv (>=1.0.1,<2.0.0)
Requires-Dist: python-jose (>=3.3.0,<4.0.0)
Requires-Dist: python-multipart (>=0.0.9,<0.0.10)
Requires-Dist: redis (>=5.2.0,<6.0.0)
Requires-Dist: setuptools (>=75.6.0,<76.0.0)
Requires-Dist: sqladmin[full] (>=0.18.0,<0.19.0)
Requires-Dist: sqlalchemy (>=2.0.32,<3.0.0)
Requires-Dist: sqlalchemy-filters (>=0.13.0,<0.14.0)
Requires-Dist: sqlmodel (>=0.0.22,<0.0.23)
Requires-Dist: sse-starlette (==1.8.2)
Requires-Dist: starlette-admin (>=0.14.1,<0.15.0)
Requires-Dist: uvicorn (>=0.30.6,<0.31.0)
Requires-Dist: websockets (>=14.1,<15.0)
